pcom/__init__.py
pcom/commands/__init__.py
pcom/commands/ascii_command.py
pcom/commands/ascii_write_command.py
pcom/commands/base_command.py
pcom/commands/binary_command.py
pcom/commands/id.py
pcom/commands/operand_request.py
pcom/commands/read_operands.py
pcom/commands/read_rtc.py
pcom/commands/set_bits.py
pcom/commands/set_rtc.py
pcom/commands/write_floats.py
pcom/commands/write_integers.py
pcom/commands/datatables/__init__.py
pcom/commands/datatables/datatable_command.py
pcom/commands/datatables/read_datatable.py
pcom/commands/datatables/structure.py
pcom/commands/datatables/write_datatable.py
pcom/errors/__init__.py
pcom/errors/pcom_error.py
pcom/plc/__init__.py
pcom/plc/base_plc.py
pcom/plc/ethernet_command_wrapper.py
pcom/plc/ethernet_plc.py
pcom/plc/serial_plc.py
pcom-0.11.dist-info/LICENSE
pcom-0.11.dist-info/METADATA
pcom-0.11.dist-info/WHEEL
pcom-0.11.dist-info/top_level.txt
pcom-0.11.dist-info/RECORD
