Metadata-Version: 2.1
Name: pcom
Version: 0.11
Summary: A basic PCOM implementation in Python
Home-page: UNKNOWN
Author: Jerther
Author-email: jtheriault@metalsartigan.com
License: MIT License
Platform: UNKNOWN
License-File: LICENSE
